07_flip_flop/modules.v
module FFD(D,clk,Q);
	input D; // Data input 
	input clk; // clock input 
	output reg Q; // output Q 
	
	always @(posedge clk) 
		begin
			Q <= D; 
		end 
endmodule

module FFD_R( D, clk, reset, Q);
	input D; // Data input 
	input clk; // clock input 
	input reset;
	output reg Q; // output Q 
	
	always @(posedge clk) 
	begin
		if (reset)
			Q <= 1'b0;
		else
			Q <= D; 
	end 
endmodule

07_flip_flop/top_tb.v
//`timescale 1 ns/10 ps

module top_tb();
	reg data, clk, reset;
	wire out;
	
	FFD_R u0 (data, clk, reset, out);
	
	initial begin
		data = 1'b0; clk = 1'b0; reset = 1'b0;
		#9 data = 1'b1;
		#13 data = 1'b0;
		#12 data = 1'b1;
		#10 ;
		$finish;
	end
	
	initial begin
        $dumpfile("top_tb.vcd");
        $dumpvars(0, top_tb);
    end
	
	always
		#5 clk = ~clk;
	
endmodule

07_flip_flop/top_tb.vcd
$date
	Mon Aug 22 12:26:19 2022
$end
$version
	Icarus Verilog
$end
$timescale
	1ps
$end
$scope module top_tb $end
$var wire 1 ! out $end
$var reg 1 " clk $end
$var reg 1 # data $end
$var reg 1 $ reset $end
$scope module u0 $end
$var wire 1 # D $end
$var wire 1 " clk $end
$var wire 1 $ reset $end
$var reg 1 ! Q $end
$upscope $end
$upscope $end
$enddefinitions $end
#0
$dumpvars
0$
0#
0"
x!
$end
#5
0!
1"
#9
1#
#10
0"
#15
1!
1"
#20
0"
#22
0#
#25
0!
1"
#30
0"
#34
1#
#35
1!
1"
