06_mux_demux_decoder/mux.v
module MUX_4x1 ( 
    input d00, d01, d10, d11,
    input s0, s1,
    output out
    ); 

 assign out = s1 ? (s0 ? d11 : d10) : (s0 ? d01 : d00); 

endmodule


module mux_8x1(
	input D0, D1, D2, D3, D4, D5, D6, D7,
	input S2, S1, S0,
	output out);
	
	reg out;
	always@(D0, D1, D2, D3, D4, D5, D6, D7, S2, S1, S0)
		begin
		case( {S2, S1, S0} )
			3'b000: out=D0;
			3'b001: out=D1;
			3'b010: out=D2;
			3'b011: out=D3;
			3'b100: out=D4;
			3'b101: out=D5;
			3'b110: out=D6;
			3'b111: out=D7;
			default: out=1'b0;
		endcase
	end
endmodule

06_mux_demux_decoder/mux_tb.v
//`timescale 1 ns/10 ps

module mux_tb();
	
	reg d0, d1, d2, d3, d4, d5, d6, d7, s0, s1, s2;
	wire out;
	
	mux_8x1 u1 (d0, d1, d2, d3, d4, d5, d6, d7, s0, s1, s2, out);
	
	initial
	begin
		$monitor("s2 %b s1 %b s0 %b => out %b", s2, s1, s0, out);
		d0 = 0; d1 = 1; d2 = 0; d3 = 0; d4 = 1; d5 = 1; d6 = 0; d7 = 0; 
		s2 = 0; s1 = 0; s0 = 0; 
		#5;
		s2 = 0; s1 = 0; s0 = 1; 
		#5;
		s2 = 0; s1 = 1; s0 = 0; 
		#5;
		s2 = 0; s1 = 1; s0 = 1; 
		#5;
		s2 = 1; s1 = 0; s0 = 0; 
		#5;
		s2 = 1; s1 = 0; s0 = 1; 
		#5;
		s2 = 1; s1 = 1; s0 = 0; 
		#5;
		s2 = 1; s1 = 1; s0 = 1;  
		#5 $finish;
	end
	
	initial begin
        $dumpfile("mux_tb.vcd");
        $dumpvars(0, mux_tb);
    end
	
endmodule

06_mux_demux_decoder/mux_tb.vcd
$date
	Mon Aug 15 20:19:13 2022
$end
$version
	Icarus Verilog
$end
$timescale
	1ps
$end
$scope module mux_tb $end
$var wire 1 ! out $end
$var reg 1 " d0 $end
$var reg 1 # d1 $end
$var reg 1 $ d2 $end
$var reg 1 % d3 $end
$var reg 1 & d4 $end
$var reg 1 ' d5 $end
$var reg 1 ( d6 $end
$var reg 1 ) d7 $end
$var reg 1 * s0 $end
$var reg 1 + s1 $end
$var reg 1 , s2 $end
$scope module u1 $end
$var wire 1 " D0 $end
$var wire 1 # D1 $end
$var wire 1 $ D2 $end
$var wire 1 % D3 $end
$var wire 1 & D4 $end
$var wire 1 ' D5 $end
$var wire 1 ( D6 $end
$var wire 1 ) D7 $end
$var wire 1 , S0 $end
$var wire 1 + S1 $end
$var wire 1 * S2 $end
$var reg 1 ! out $end
$upscope $end
$upscope $end
$enddefinitions $end
#0
$dumpvars
0,
0+
0*
0)
0(
1'
1&
0%
0$
1#
0"
0!
$end
#5
1!
1*
#10
0!
0*
1+
#15
1*
#20
1!
0*
0+
1,
#25
1*
#30
0!
0*
1+
#35
1*
