10_factoring_semaforo/fsm_parade.v
module FSM_parade(input P, R, clk, reset, output reg M);
    reg state, next_state;
    parameter S0 = 1'b0, S1 = 1'b1;
    parameter on = 1'b1, off = 1'b0;

    // Nube combinacional para calcular el estado futuro

    always @ (P or R or state) begin
        case (state)
            S0: begin
                    if (P == 1)
                        next_state <= S1; 
                    else // siempre completamos el if-else
                        next_state <= S0; 
                end
            S1: begin
                    if (R == 1)
                        next_state <= S0; 
                    else // siempre completamos el if-else
                        next_state <= S1; 
                end
            default: next_state <= S0; // Incluímos el 'default' para que la sintetización sea combinacional
        endcase
    end

    // Banco de flip flops
    always @ (posedge clk or posedge reset) begin

        if (reset == 1)
            state <= S0;
        else
            state <= next_state;
    end
	initial state <= 1'b0;
	
    // Nube combinacional para calcular las salidas
    always @ (state) begin
        case (state)
            S0: M = off;
            S1: M = on;
            default: M = off;
        endcase
    end

endmodule

10_fatoring_semaforo/fsm_moore.v
module FSM_moore(input TA, TB, M, clk, reset, output reg [2:0] LA, LB);
    reg [1:0] state, next_state;
    parameter S0 = 2'b00, S1 = 2'b01, S2 = 2'b10, S3 = 2'b11;
    parameter green = 3'b001, yellow = 3'b010, red = 3'b100;

    // Nube combinacional para calcular el estado futuro

    always @ (TA or TB or state) begin
        case (state)
            S0: begin
                    if (TA == 1)
                        next_state <= S0; // No incluimos 'begin' y 'end' porque sólo es 1 instrucción dentro del 'case'
                    else
                        next_state <= S1;
                end
            S1: next_state <= S2;
            S2: if (TB == 1 || M == 1) 
					next_state <= S2;
                else
					next_state <= S3;
            S3: next_state <= S0;
            default: next_state <= S0; // Incluímos el 'default' para que la sintetización sea lógica combinacional y no secuencial
        endcase
    end

    // Banco de flip flops

    always @ (posedge clk or posedge reset) begin

        if (reset == 1)
            state <= S0;
        else
            state <= next_state;
    end
	initial state <= 2'b00;
	
    // Nube combinacional para calcular las salidas
	always @ (state) begin
        case (state)
            S0: begin LA = green; LB = red; end
            S1: begin LA = yellow; LB = red; end
            S2: begin LA = red; LB = green; end
            S3: begin LA = red; LB = yellow; end
            default: begin LA = red; LB = red; end
        endcase
    end

endmodule

10_fatoring_semaforo/semaforo.v
module semaforo_completo (
	input TA, TB, P, R, clk, reset,
	output [2:0] LA, LB
	);
	
	// interconexión de las FSMs
	wire M;
	FSM_moore  FSM1(TA, TB, M, clk, reset, LA, LB);
	FSM_parade FSM2(P, R, clk, reset, M);
	
endmodule

10_fatoring_semaforo/top_tb.v

module top_tb();

    reg TA, TB, P, R, clk, reset;
    wire [2:0] LA, LB;

    semaforo_completo U1(TA, TB, P, R, clk, reset, LA, LB);

    initial begin
        $dumpfile("top_tb.vcd");
        $dumpvars(0, top_tb);
    end

    initial
        #200 $finish;

    always
        #5 clk = ~clk;

    initial begin
        clk = 0; TA = 0; TB = 0; 
		P = 0; R = 0; reset = 1;

        #7
        reset = 0;

        #30
        TA = 1;
        #10
        TB = 1;
        #20
        TA = 0;
        #30
        TB = 0;
        #10
        P = 1;
        #30
        P = 0;
        R = 0;

    end
endmodule

10_fatoring_semaforo/top_tb.vcd
$date
	Thu Sep 01 20:50:50 2022
$end
$version
	Icarus Verilog
$end
$timescale
	1s
$end
$scope module top_tb $end
$var wire 3 ! LB [2:0] $end
$var wire 3 " LA [2:0] $end
$var reg 1 # P $end
$var reg 1 $ R $end
$var reg 1 % TA $end
$var reg 1 & TB $end
$var reg 1 ' clk $end
$var reg 1 ( reset $end
$scope module U1 $end
$var wire 1 # P $end
$var wire 1 $ R $end
$var wire 1 % TA $end
$var wire 1 & TB $end
$var wire 1 ' clk $end
$var wire 1 ( reset $end
$var wire 1 ) M $end
$var wire 3 * LB [2:0] $end
$var wire 3 + LA [2:0] $end
$scope module FSM1 $end
$var wire 1 % TA $end
$var wire 1 & TB $end
$var wire 1 ' clk $end
$var wire 1 ( reset $end
$var wire 1 ) M $end
$var reg 3 , LA [2:0] $end
$var reg 3 - LB [2:0] $end
$var reg 2 . next_state [1:0] $end
$var reg 2 / state [1:0] $end
$upscope $end
$scope module FSM2 $end
$var wire 1 # P $end
$var wire 1 $ R $end
$var wire 1 ' clk $end
$var wire 1 ( reset $end
$var reg 1 ) M $end
$var reg 1 0 next_state $end
$var reg 1 1 state $end
$upscope $end
$upscope $end
$upscope $end
$enddefinitions $end
#0
$dumpvars
01
00
b0 /
b1 .
b100 -
b1 ,
b1 +
b100 *
0)
1(
0'
0&
0%
0$
0#
b1 "
b100 !
$end
#5
1'
#7
0(
#10
0'
#15
b10 .
b10 "
b10 +
b10 ,
b1 /
1'
#20
0'
#25
b11 .
b1 !
b1 *
b1 -
b100 "
b100 +
b100 ,
b10 /
1'
#30
0'
#35
b0 .
b10 !
b10 *
b10 -
b11 /
1'
#37
1%
#40
0'
#45
b100 !
b100 *
b100 -
b1 "
b1 +
b1 ,
b0 /
1'
#47
1&
#50
0'
#55
1'
#60
0'
#65
1'
#67
b1 .
0%
#70
0'
#75
b10 .
b10 "
b10 +
b10 ,
b1 /
1'
#80
0'
#85
b1 !
b1 *
b1 -
b100 "
b100 +
b100 ,
b10 /
1'
#90
0'
#95
1'
#97
b11 .
0&
#100
0'
#105
b0 .
b10 !
b10 *
b10 -
b11 /
1'
#107
10
1#
#110
0'
#115
b1 .
b100 !
b100 *
b100 -
b1 "
b1 +
b1 ,
1)
b0 /
11
1'
#120
0'
#125
b10 .
b10 "
b10 +
b10 ,
b1 /
1'
#130
0'
#135
b1 !
b1 *
b1 -
b100 "
b100 +
b100 ,
b10 /
1'
#137
0#
