08_fsm_semaforno_moore/decoder.v
module DECODER_2x4 ( 
    input [1:0] A,
    output reg [3:0] Y
    );
    always @(A) begin
        case (A)
            2'b00 :
                Y = 4'b0001;
            2'b01 : 
                Y = 4'b0010;
            2'b10 : 
                Y = 4'b0100;
            2'b11 : 
                Y = 4'b1000;
        endcase   
    end
endmodule

08_fsm_moore/fsm_moore.v
 module FSM_moore(input TA, TB, clk, reset, output [1:0] LA, LB);
    wire [1:0] next_state, LA, LB;	// combinacional
	reg [1:0] state;		// secuencial
    
    // Nube combinacional para calcular el estado futuro
	assign next_state[1] = state[1] ^ state[0];
	assign next_state[0] = (~state[1] & ~state[0] & ~TA) | (state[1] & ~state[0] & ~TB);

    // Banco de flip flops
    always @ (posedge clk or posedge reset) begin

        if (reset == 1)
            state <= 2'b00;
        else
            state <= next_state;
    end

	// valor inicial para la simulación
	// se puede obviar si usamos el reset
	initial state <= 2'b00;
	
    // Nube combinacional para calcular las salidas
    // 00 = green		01 = yellow		10 == red
	assign LA[1] = state[1];
	assign LA[0] = ~state[1]&state[0];
	assign LB[1] = ~state[1];
	assign LB[0] = state[1]&state[0];
	
endmodule

08_fsm_semaforno_moore/semaforo.v
module semaforo_completo (
	input TA, TB, clk,
	output [2:0] LA, LB
	);
    wire [2:0] LA, LB;		// decodificada
	wire [1:0] LA_coded, LB_coded; 	// codificada
	wire [3:0] LA_decoded, LB_decoded; 	// 4 bits
	
	// señal de reset
	wire reset;
	assign reset = 1'b0;
	
	// FSM con salidas codificadas
	FSM_moore FSM1(TA, TB, clk, reset, LA_coded, LB_coded);
	
	DECODER_2x4 DEC0(LA_coded, LA_decoded);
	DECODER_2x4 DEC1(LB_coded, LB_decoded);
	
	assign LA = LA_decoded[2:0];
	assign LB = LB_decoded[2:0];
	
endmodule

09_fsm_moore_behavorial/top_tb.v

module top_tb();

    reg TA, TB, clk;
    wire [2:0] LA, LB;

    semaforo_completo U1(TA, TB, clk, LA, LB);

    initial begin
        $dumpfile("top_tb.vcd");
        $dumpvars(0, top_tb);
    end

    initial
        #150 $finish;

    always
        #5 clk = ~clk;

    initial begin
        clk = 0; TA = 0; TB = 0; //reset = 0;

        //#13
        //reset = 1;
        //#10
        //reset = 0; // esperamos 10s para garantizar que ya pasó 1 flanco de reloj

        #30
        TA = 1;
        #10
        TB = 1;
        #20
        TA = 0;
        #30
        TB = 0;
        #10
        TA = 1;

    end
endmodule

08_fsm_moore/top_tb.vcd
$date
	Thu Aug 25 21:34:35 2022
$end
$version
	Icarus Verilog
$end
$timescale
	1ps
$end
$scope module top_tb $end
$var wire 3 ! LB [2:0] $end
$var wire 3 " LA [2:0] $end
$var reg 1 # TA $end
$var reg 1 $ TB $end
$var reg 1 % clk $end
$scope module U1 $end
$var wire 1 # TA $end
$var wire 1 $ TB $end
$var wire 1 % clk $end
$var wire 1 & reset $end
$var wire 4 ' LB_decoded [3:0] $end
$var wire 2 ( LB_coded [1:0] $end
$var wire 3 ) LB [2:0] $end
$var wire 4 * LA_decoded [3:0] $end
$var wire 2 + LA_coded [1:0] $end
$var wire 3 , LA [2:0] $end
$scope module DEC0 $end
$var wire 2 - A [1:0] $end
$var reg 4 . Y [3:0] $end
$upscope $end
$scope module DEC1 $end
$var wire 2 / A [1:0] $end
$var reg 4 0 Y [3:0] $end
$upscope $end
$scope module FSM1 $end
$var wire 1 # TA $end
$var wire 1 $ TB $end
$var wire 1 % clk $end
$var wire 1 & reset $end
$var wire 2 1 next_state [1:0] $end
$var wire 2 2 LB [1:0] $end
$var wire 2 3 LA [1:0] $end
$var reg 2 4 state [1:0] $end
$upscope $end
$upscope $end
$upscope $end
$enddefinitions $end
#0
$dumpvars
b0 4
b0 3
b10 2
b1 1
b100 0
b10 /
b1 .
b0 -
b1 ,
b0 +
b1 *
b100 )
b10 (
b100 '
0&
0%
0$
0#
b1 "
b100 !
$end
#5
b10 "
b10 ,
b10 *
b10 .
b10 1
b1 +
b1 -
b1 3
b1 4
1%
#10
0%
#15
b11 1
b1 !
b1 )
b100 "
b100 ,
b1 '
b1 0
b100 *
b100 .
b0 (
b0 /
b0 2
b10 +
b10 -
b10 3
b10 4
1%
#20
0%
#25
b10 !
b10 )
b10 '
b10 0
b0 1
b1 (
b1 /
b1 2
b11 4
1%
#30
0%
1#
#35
b100 !
b100 )
b1 "
b1 ,
b100 '
b100 0
b1 *
b1 .
b10 (
b10 /
b10 2
b0 +
b0 -
b0 3
b0 4
1%
#40
0%
1$
#45
1%
#50
0%
#55
1%
#60
b1 1
0%
0#
#65
b10 "
b10 ,
b10 *
b10 .
b10 1
b1 +
b1 -
b1 3
b1 4
1%
#70
0%
#75
b1 !
b1 )
b100 "
b100 ,
b1 '
b1 0
b100 *
b100 .
b0 (
b0 /
b0 2
b10 +
b10 -
b10 3
b10 4
1%
#80
0%
#85
1%
#90
b11 1
0%
0$
#95
b10 !
b10 )
b10 '
b10 0
b0 1
b1 (
b1 /
b1 2
b11 4
1%
#100
0%
1#
#105
b100 !
b100 )
b1 "
b1 ,
b100 '
b100 0
b1 *
b1 .
b10 (
b10 /
b10 2
b0 +
b0 -
b0 3
b0 4
1%
