08_fsm_moore/fsm_moore.v
 module FSM_moore(input TA, TB, clk, reset, output reg [1:0] LA, LB);
    reg [1:0] state, next_state;
    parameter S0 = 2'b00, S1 = 2'b01, S2 = 2'b10, S3 = 2'b11;
    parameter green = 2'b00, yellow = 2'b01, red = 2'b10;

    // Nube combinacional para calcular el estado futuro

    always @ (TA or TB or state) begin
        case (state)
            S0: begin
                    if (TA == 1)
                        next_state <= S0; // No incluimos 'begin' y 'end' porque sólo es 1 instrucción dentro del 'case'
                    else
                        next_state <= S1;
                end
            S1: next_state <= S2;
            S2: if (TB == 1) next_state <= S2;
                else next_state <= S3;
            S3: next_state <= S0;
            default: next_state <= S0; // Incluímos el 'default' para que la sintetización sea lógica combinacional y no secuencial
        endcase
    end

    // Banco de flip flops

    always @ (posedge clk or posedge reset) begin

        if (reset == 1)
            state <= S0;
        else
            state <= next_state;
    end

    // Nube combinacional para calcular las salidas
    // 00 = green
    // 01 = yellow
    // 10 == red

    always @ (state) begin
        case (state)
            S0: begin LA = green; LB = red; end
            S1: begin LA = yellow; LB = red; end
            S2: begin LA = red; LB = green; end
            S3: begin LA = red; LB = yellow; end
            default: begin LA = red; LB = red; end
        endcase
    end

endmodule

08_fsm_moore/top_tb.v

module testbench();

    reg TA, TB, clk, reset;
    wire [1:0] LA, LB;

    FSM_moore U1(TA, TB, clk, reset, LA, LB);

    initial begin
        $dumpfile("top_tb.vcd");
        $dumpvars(0, testbench);
    end

    initial
        #150 $finish;

    always
        #5 clk = ~clk;

    initial begin
        clk = 0; reset = 0; TA = 0; TB = 0;

        #13
        reset = 1;
        #10
        reset = 0; // esperamos 10s para garantizar que ya pasó 1 flanco de reloj

        #30
        TA = 1;
        #10
        TB = 1;
        #20
        TA = 0;
        #30
        TB = 0;
        #10
        TA = 1;

    end
endmodule

fsm/top_tb.vcd
$date
	Mon Aug 30 11:27:59 2021
$end
$version
	Icarus Verilog
$end
$timescale
	1ps
$end
$scope module testbench $end
$var wire 2 ! LB [1:0] $end
$var wire 2 " LA [1:0] $end
$var reg 1 # TA $end
$var reg 1 $ TB $end
$var reg 1 % clk $end
$var reg 1 & reset $end
$scope module U1 $end
$var wire 1 # TA $end
$var wire 1 $ TB $end
$var wire 1 % clk $end
$var wire 1 & reset $end
$var reg 2 ' LA [1:0] $end
$var reg 2 ( LB [1:0] $end
$var reg 2 ) next_state [1:0] $end
$var reg 2 * state [1:0] $end
$upscope $end
$upscope $end
$enddefinitions $end
#0
$dumpvars
bx *
b0 )
bx (
bx '
0&
0%
0$
0#
bx "
bx !
$end
#5
b1 )
b10 !
b10 (
b0 "
b0 '
b0 *
1%
#10
0%
#13
1&
#15
1%
#20
0%
#23
0&
#25
b10 )
b1 "
b1 '
b1 *
1%
#30
0%
#35
b11 )
b0 !
b0 (
b10 "
b10 '
b10 *
1%
#40
0%
#45
b0 )
b1 !
b1 (
b11 *
1%
#50
0%
#53
1#
#55
b10 !
b10 (
b0 "
b0 '
b0 *
1%
#60
0%
#63
1$
#65
1%
#70
0%
#75
1%
#80
0%
#83
b1 )
0#
#85
b10 )
b1 "
b1 '
b1 *
1%
#90
0%
#95
b0 !
b0 (
b10 "
b10 '
b10 *
1%
#100
0%
#105
1%
#110
0%
#113
b11 )
0$
#115
b0 )
b1 !
b1 (
b11 *
1%
#120
0%
#123
1#
#125
b10 !
b10 (
b0 "
b0 '
b0 *
1%
