13_pulse_generator/modules.v
module pulse_generator(input A, clk, reset, output reg pulse);
    reg [1:0] state, next_state;
    parameter S0 = 2'b00, S1 = 2'b01, S2 = 2'b10;
    
    // Nube combinacional para calcular el estado futuro y salidas

    always @ (A or state) begin
        case (state)
            S0: begin
                    if (A == 1)
                        next_state <= S1; 
                    else begin
                        next_state <= S0;
					end
                end
            S1: begin
                    if (A == 1) 
                        next_state <= S2; 
                    else 
                        next_state <= S0;
                end
            S2: begin
                    if (A == 1) 
                        next_state <= S2; 
                    else 
                        next_state <= S0;
                end
            default: 
				next_state <= S0; 
        endcase
    end

    // Banco de flip flops
    always @ (posedge clk or posedge reset) begin

        if (reset == 1)
            state <= S0;
        else
            state <= next_state;
    end
	initial state <= 2'b00;
	
    // Nube combinacional para calcular las salidas
	 always @ (state) begin
        case (state)
            S0: pulse <= 1'b0;
            S1: pulse <= 1'b1;
            S2: pulse <= 1'b0;
            default: pulse <= 1'b0;
        endcase
    end

endmodule

13_pulse_generator/top_tb.v

module top_tb();
    reg A, reset, clk;
    wire pulse;

    pulse_generator U1(A, clk, reset, pulse);
	// variaciones en las entradas
    initial begin
        clk = 0; reset = 1;
		#10 reset = 0;
		#10 A = 1;
		#30 A = 0;
		#10 A = 1;
		#60 A = 0;
    end
    // archivo de GTKwave y fin de la simulación
    initial begin
        $dumpfile("top_tb.vcd");
        $dumpvars(0, top_tb);
		#150 $finish;
    end
	// señal de reloj
    always
        #5 clk = ~clk;

endmodule

13_pulse_generator/top_tb.vcd
$date
	Mon Sep 12 18:19:23 2022
$end
$version
	Icarus Verilog
$end
$timescale
	1ps
$end
$scope module top_tb $end
$var wire 1 ! pulse $end
$var reg 1 " A $end
$var reg 1 # clk $end
$var reg 1 $ reset $end
$scope module U1 $end
$var wire 1 " A $end
$var wire 1 # clk $end
$var wire 1 $ reset $end
$var reg 2 % next_state [1:0] $end
$var reg 1 ! pulse $end
$var reg 2 & state [1:0] $end
$upscope $end
$upscope $end
$enddefinitions $end
#0
$dumpvars
b0 &
b0 %
1$
0#
x"
0!
$end
#5
1#
#10
0#
0$
#15
1#
#20
b1 %
0#
1"
#25
1!
b10 %
b1 &
1#
#30
0#
#35
0!
b10 &
1#
#40
0#
#45
1#
#50
b0 %
0#
0"
#55
b0 &
1#
#60
b1 %
0#
1"
#65
1!
b10 %
b1 &
1#
#70
0#
#75
0!
b10 &
1#
