12_timer/modules.v
module tmr(input clk, reset, output reg [7:0] count);
    
    // funcionamiento del timer
    always @ (posedge clk or posedge reset) begin

        if (reset == 1)
            count <= 8'b0;
        else
            count <= count + 1;
    end
	// condición inicial de simulación
	initial count <= 8'b0;
	
endmodule

12_timer/top_tb.v

module top_tb();
    reg reset, clk;
    wire [7:0] count;

    tmr U1(clk, reset, count);
	// variaciones en las entradas
    initial begin
        clk = 0; reset = 1;
		#15 reset = 0;
		#80 reset = 1;
		#5 reset = 0;
    end
    // archivo de GTKwave y fin de la simulación
    initial begin
        $dumpfile("top_tb.vcd");
        $dumpvars(0, top_tb);
		#150 $finish;
    end
	// señal de reloj
    always
        #5 clk = ~clk;

endmodule

12_timer/top_tb.vcd
$date
	Mon Sep 12 18:06:32 2022
$end
$version
	Icarus Verilog
$end
$timescale
	1ps
$end
$scope module top_tb $end
$var wire 8 ! count [7:0] $end
$var reg 1 " clk $end
$var reg 1 # reset $end
$scope module U1 $end
$var wire 1 " clk $end
$var wire 1 # reset $end
$var reg 8 $ count [7:0] $end
$upscope $end
$upscope $end
$enddefinitions $end
#0
$dumpvars
b0 $
1#
0"
b0 !
$end
#5
1"
#10
0"
#15
b1 !
b1 $
1"
0#
#20
0"
#25
b10 !
b10 $
1"
#30
0"
#35
b11 !
b11 $
1"
#40
0"
#45
b100 !
b100 $
1"
#50
0"
#55
b101 !
b101 $
1"
#60
0"
#65
b110 !
b110 $
1"
#70
0"
#75
b111 !
b111 $
1"
#80
0"
#85
b1000 !
b1000 $
1"
#90
0"
#95
b0 !
b0 $
1"
1#
#100
0"
0#
#105
b1 !
b1 $
1"
#110
0"
#115
b10 !
b10 $
1"
#120
0"
#125
b11 !
b11 $
1"
#130
0"
#135
b100 !
b100 $
1"
#140
0"
#145
b101 !
b101 $
1"
